discorpy/__init__.py
discorpy/losa/__init__.py
discorpy/losa/loadersaver.py
discorpy/post/__init__.py
discorpy/post/postprocessing.py
discorpy/prep/__init__.py
discorpy/prep/linepattern.py
discorpy/prep/preprocessing.py
discorpy/proc/__init__.py
discorpy/proc/processing.py
discorpy/util/__init__.py
discorpy/util/utility.py
discorpy-1.7.0.dist-info/licenses/LICENSE
discorpy-1.7.0.dist-info/METADATA
discorpy-1.7.0.dist-info/WHEEL
discorpy-1.7.0.dist-info/top_level.txt
discorpy-1.7.0.dist-info/RECORD
