Metadata-Version: 2.4
Name: discorpy
Version: 1.7.0
Summary: Correction for radial distortion and perspective distortion in Python
Home-page: https://github.com/DiamondLightSource/discorpy
Download-URL: https://github.com/DiamondLightSource/discorpy.git
Author: Nghia Vo
Author-email: nvo@bnl.gov
License: Apache-2.0
Keywords: Distortion correction,Tomography,Radial lens distortion,Camera calibration,Perspective distortion,Fisheye distortion
Platform: Any
Classifier: Programming Language :: Python :: 3
Classifier: Intended Audience :: Science/Research
Classifier: Operating System :: OS Independent
Classifier: Natural Language :: English
Classifier: Topic :: Scientific/Engineering :: Image Processing
Requires-Python: >=3.9
License-File: LICENSE
Requires-Dist: scikit-image
Requires-Dist: scipy
Requires-Dist: h5py
Requires-Dist: pillow
Requires-Dist: matplotlib
Requires-Dist: numpy
Dynamic: author
Dynamic: author-email
Dynamic: classifier
Dynamic: description
Dynamic: description-content-type
Dynamic: download-url
Dynamic: home-page
Dynamic: keywords
Dynamic: license
Dynamic: license-file
Dynamic: platform
Dynamic: requires-dist
Dynamic: requires-python
Dynamic: summary
